bits/__init__.py
bits/jenkins/__init__.py
bits_jenkins-1.0.0.dist-info/METADATA
bits_jenkins-1.0.0.dist-info/WHEEL
bits_jenkins-1.0.0.dist-info/top_level.txt
bits_jenkins-1.0.0.dist-info/RECORD
