Metadata-Version: 2.1
Name: bits-jenkins
Version: 1.0.0
Summary: BITS Jenkins
Home-page: UNKNOWN
Author: Lukas Karlsson
Author-email: karlsson@broadinstitute.org
License: Apache Software License
Platform: UNKNOWN
Requires-Dist: python-jenkins
